pygitter/Repo.py
pygitter/__init__.py
pygitter-0.0.6.dist-info/LICENSE
pygitter-0.0.6.dist-info/METADATA
pygitter-0.0.6.dist-info/WHEEL
pygitter-0.0.6.dist-info/top_level.txt
pygitter-0.0.6.dist-info/RECORD
