Metadata-Version: 2.1
Name: pygitter
Version: 0.0.6
Summary: A python wrapper for git repositories
Home-page: https://github.com/minamaged113/pygitter
Author: Mina Ghobrial
Author-email: minamaged113@gmail.com
Project-URL: Bug Tracker, https://github.com/minamaged113/pygitter/issues
Classifier: Programming Language :: Python :: 3.7
Classifier: Programming Language :: Python :: 3.8
Classifier: Programming Language :: Python :: 3.9
Classifier: Programming Language :: Python :: 3.10
Classifier: License :: OSI Approved :: MIT License
Classifier: Operating System :: OS Independent
Requires-Python: >=3.7
License-File: LICENSE
